uedgetools-1.3.3.dist-info/licenses/LICENSE
uedgetools-1.3.3.dist-info/licenses/NOTICE.md
uetools/VERSION
uetools/__init__.py
uetools/geometryTest.py
uetools/UeBayesian/BayesDemo.py
uetools/UeBayesian/BayesUtility.py
uetools/UeBayesian/Bayesian.py
uetools/UeBayesian/__init__.py
uetools/UeCampaign/Campaign.py
uetools/UeCampaign/__init__.py
uetools/UeCase/Case.py
uetools/UeCase/Config.py
uetools/UeCase/Input.py
uetools/UeCase/Parallel.py
uetools/UeCase/Save.py
uetools/UeCase/__init__.py
uetools/UeCherab/Cherab.py
uetools/UeCherab/README.md
uetools/UeCherab/__init__.py
uetools/UeCherab/bolometer_sensitivity.py
uetools/UeCherab/triangulate.py
uetools/UeCherab/d3d/__init__.py
uetools/UeCherab/d3d/bolometer.py
uetools/UeCherab/d3d/wall.py
uetools/UeDEGAS/Coupling.py
uetools/UeDEGAS/__init__.py
uetools/UeDashboard/Dashboard.py
uetools/UeDashboard/__init__.py
uetools/UeDashboard/range_slider.py
uetools/UeDatabase/DB_1Dplots.py
uetools/UeDatabase/DB_2Dplots.py
uetools/UeDatabase/Database.py
uetools/UeDatabase/__init__.py
uetools/UeDiagnostics/Diagnostics.py
uetools/UeDiagnostics/__init__.py
uetools/UeDiagnostics/d3d_bolometer_projection.hdf5
uetools/UeGrid/Grid.py
uetools/UeGrid/__init__.py
uetools/UePlot/CasePlot.py
uetools/UePlot/Plot.py
uetools/UePlot/__init__.py
uetools/UePostproc/Postproc.py
uetools/UeSolver/Solver.py
uetools/UeSolver/SolverStrategy.py
uetools/UeSolver/__init__.py
uetools/UeUtils/ADASclass.py
uetools/UeUtils/AboutSetup.py
uetools/UeUtils/Convert.py
uetools/UeUtils/Interpolate.py
uetools/UeUtils/Lookup.py
uetools/UeUtils/RadTransp.py
uetools/UeUtils/Tools.py
uetools/UeUtils/Tracker.py
uetools/UeUtils/Utilities.py
uetools/UeUtils/__init__.py
uetools/ignore/Track.py
uetools/ignore/watch.py
uetools/ignore/UeGui/Commands.py
uetools/ignore/UeGui/ScrollableNotebook.py
uetools/ignore/UeGui/__init__.py
uetools/ignore/UeGui/example/README.md
uetools/ignore/UeGui/example/d3dHsm.h5
uetools/ignore/UeGui/example/ehr2.dat
uetools/ignore/UeGui/example/rd_d3dHsm_in.py
uetools/ignore/UeGui/example/run.py
uetools/yamls/__init__.py
uetools/yamls/plots.yaml
uedgetools-1.3.3.dist-info/METADATA
uedgetools-1.3.3.dist-info/WHEEL
uedgetools-1.3.3.dist-info/entry_points.txt
uedgetools-1.3.3.dist-info/top_level.txt
uedgetools-1.3.3.dist-info/RECORD
