Metadata-Version: 2.4
Name: uedgetools
Version: 1.3.3
Summary: A utility tool for the UEDGE multi-fluid plasma-edge code
Author-email: Andreas Holm <holm10@llnl.gov>
License:                   GNU LESSER GENERAL PUBLIC LICENSE
Project-URL: Homepage, https://github.com/LLNL/UETOOLS
Project-URL: Issues, https://github.com/LLNL/UETOOLS/issues
Keywords: uedge,fusion,plasma,physics,fluid
Classifier: Programming Language :: Python :: 3
Classifier: License :: OSI Approved :: GNU Lesser General Public License v2 (LGPLv2)
Classifier: Operating System :: Unix
Requires-Python: >=3.8
License-File: LICENSE
License-File: NOTICE.md
Requires-Dist: numpy
Requires-Dist: scipy
Requires-Dist: h5py
Requires-Dist: pyaml
Requires-Dist: Forthon
Requires-Dist: matplotlib
Requires-Dist: shapely
Requires-Dist: h5pickle
Requires-Dist: PyQt5
Requires-Dist: bayesian-optimization>=3
Provides-Extra: parallel
Requires-Dist: inspect; extra == "parallel"
Requires-Dist: uuid; extra == "parallel"
Requires-Dist: pickle; extra == "parallel"
Provides-Extra: uedge
Requires-Dist: Forthon; extra == "uedge"
Requires-Dist: uedge; extra == "uedge"
Dynamic: license-file
